[{"colour":"amber","time":[2018,4,12,15,42,34],"number":1},{"colour":"amber","time":[2018,4,12,15,42,43],"number":2},{"colour":"amber","time":[2018,4,12,15,43,6],"number":3},{"colour":"amber","time":[2018,4,12,15,43,37],"number":4},{"colour":"amber","time":[2018,4,12,15,43,47],"number":5},{"colour":"amber","time":[2018,4,12,15,44,6],"number":6},{"colour":"amber","time":[2018,4,12,15,44,12],"number":7},{"colour":"green","time":[2018,4,12,15,44,22],"number":8},{"colour":"green","time":[2018,4,12,15,45,16],"number":9},{"colour":"green","time":[2018,4,12,15,45,43],"number":10},{"colour":"amber","time":[2018,4,12,15,46,37],"number":11},{"colour":"amber","time":[2018,4,12,15,47,11],"number":12},{"colour":"amber","time":[2018,4,12,15,47,27],"number":13},{"colour":"amber","time":[2018,4,12,15,47,49],"number":14},{"colour":"amber","time":[2018,4,12,15,47,57],"number":15},{"colour":"amber","time":[2018,4,12,15,48,12],"number":16},{"colour":"amber","time":[2018,4,12,15,48,53],"number":17},{"colour":"amber","time":[2018,4,12,15,49,5],"number":18},{"colour":"amber","time":[2018,4,12,15,49,34],"number":19},{"colour":"amber","time":[2018,4,12,15,49,48],"number":20},{"colour":"amber","time":[2018,4,12,15,50,1],"number":21}]